README.rst
setup.cfg
setup.py
drf_nested_views/__init__.py
drf_nested_views/generics.py
drf_nested_views/mixins.py
drf_nested_views/viewsets.py
drf_nested_views.egg-info/PKG-INFO
drf_nested_views.egg-info/SOURCES.txt
drf_nested_views.egg-info/dependency_links.txt
drf_nested_views.egg-info/top_level.txt