Metadata-Version: 1.1
Name: drf-nested-views
Version: 1.0.0
Summary: A set of views to work with drf-nested-routers
Home-page: https://github.com/weynelucas/drf-nested-views/
Author: Lucas Weyne
Author-email: weynelucas@gmail.com
License: UNKNOWN
Download-URL: https://github.com/weynelucas/drf-nested-views/archive/1.0.0.tar.gz
Keywords: django rest framework drf nested routers views drf-nested-routers drf-nested-views
Platform: UNKNOWN
Classifier: Development Status :: 5 - Production/Stable
Classifier: Framework :: Django
Classifier: Intended Audience :: Developers
Classifier: Topic :: Internet :: WWW/HTTP
Classifier: License :: OSI Approved :: MIT License
Classifier: Programming Language :: Python :: 3
Classifier: Programming Language :: Python :: 3.3
Classifier: Programming Language :: Python :: 3.4
Classifier: Programming Language :: Python :: 3.5
Classifier: Programming Language :: Python :: 3.6
